ark/__init__.py
ark/admin.py
ark/apps.py
ark/arklet.http
ark/forms.py
ark/management/__init__.py
ark/management/commands/__init__.py
ark/management/commands/mintarks.py
ark/migrations/0001_initial.py
ark/migrations/0002_allow_blank_ark_model_fields.py
ark/migrations/0003_set_defaults_in_db.py
ark/migrations/__init__.py
ark/models.py
ark/utils.py
ark/views.py
ark_import/__init__.py
ark_import/__main__.py
ark_import/sample_noid_output.txt
arklet-0.1.0.dist-info/entry_points.txt
arklet-0.1.0.dist-info/LICENSE
arklet-0.1.0.dist-info/WHEEL
arklet-0.1.0.dist-info/METADATA
arklet-0.1.0.dist-info/RECORD
