Metadata-Version: 2.1
Name: arklet
Version: 0.1.0
Summary: An unassuming ARK minter, binder, and resolver
Home-page: https://github.com/internetarchive/arklet
License: MIT
Author: Alex Dempsey
Author-email: avdempsey@archive.org
Requires-Python: >=3.7.2,<4.0
Classifier: Development Status :: 4 - Beta
Classifier: Environment :: Web Environment
Classifier: Framework :: Django
Classifier: Framework :: Django :: 3.2
Classifier: Framework :: Django :: 4.0
Classifier: Framework :: Django :: 4.1
Classifier: Intended Audience :: Developers
Classifier: License :: OSI Approved :: MIT License
Classifier: Operating System :: OS Independent
Classifier: Programming Language :: Python
Classifier: Programming Language :: Python :: 3
Classifier: Programming Language :: Python :: 3 :: Only
Classifier: Programming Language :: Python :: 3.10
Classifier: Programming Language :: Python :: 3.11
Classifier: Programming Language :: Python :: 3.7
Classifier: Programming Language :: Python :: 3.8
Classifier: Programming Language :: Python :: 3.9
Classifier: Topic :: Internet :: WWW/HTTP
Classifier: Topic :: Internet :: WWW/HTTP :: Dynamic Content
Provides-Extra: environ
Provides-Extra: postgres
Provides-Extra: sentry
Requires-Dist: Django (>=3.2); python_version >= "3.8"
Requires-Dist: Django (>=3.2,<3.3); python_version >= "3.7" and python_version < "3.8"
Requires-Dist: django-environ (>=0.8.1,<0.9.0); extra == "environ"
Requires-Dist: psycopg2 (>=2.7,<3.0); extra == "postgres"
Requires-Dist: sentry-sdk (>=1.5.12,<2.0.0); extra == "sentry"
Project-URL: Repository, https://github.com/internetarchive/arklet
